staplus_client/__init__.py
staplus_client/__version__.py
staplus_client/utils.py
staplus_client/dao/__init__.py
staplus_client/dao/actuator.py
staplus_client/dao/base.py
staplus_client/dao/campaign.py
staplus_client/dao/datastream.py
staplus_client/dao/features_of_interest.py
staplus_client/dao/historical_location.py
staplus_client/dao/license.py
staplus_client/dao/location.py
staplus_client/dao/multi_datastream.py
staplus_client/dao/observation.py
staplus_client/dao/observation_group.py
staplus_client/dao/observedproperty.py
staplus_client/dao/party.py
staplus_client/dao/relation.py
staplus_client/dao/sensor.py
staplus_client/dao/task.py
staplus_client/dao/tasking_capability.py
staplus_client/dao/thing.py
staplus_client/model/__init__.py
staplus_client/model/campaign.py
staplus_client/model/datastream.py
staplus_client/model/entity.py
staplus_client/model/feature_of_interest.py
staplus_client/model/historical_location.py
staplus_client/model/license.py
staplus_client/model/location.py
staplus_client/model/multi_datastream.py
staplus_client/model/observation.py
staplus_client/model/observation_group.py
staplus_client/model/observedproperty.py
staplus_client/model/party.py
staplus_client/model/relation.py
staplus_client/model/sensor.py
staplus_client/model/thing.py
staplus_client/model/ext/__init__.py
staplus_client/model/ext/entity_list.py
staplus_client/model/ext/entity_type.py
staplus_client/model/ext/unitofmeasurement.py
staplus_client/query/__init__.py
staplus_client/query/query.py
staplus_client/service/BearerAuth.py
staplus_client/service/__init__.py
staplus_client/service/auth_handler.py
staplus_client/service/staplusservice.py
staplus_client-0.3.4.dist-info/licenses/LICENSE
staplus_client-0.3.4.dist-info/METADATA
staplus_client-0.3.4.dist-info/WHEEL
staplus_client-0.3.4.dist-info/top_level.txt
staplus_client-0.3.4.dist-info/RECORD
