Metadata-Version: 2.4
Name: staplus-client
Version: 0.3.4
Summary: A client library to facilitate interaction with a STAplus Server
Home-page: https://github.com/securedimensions/STAplus-Python-Client
Author: Andreas Matheus
Author-email: andreas.matheus@secure-dimensions.de
License: LGPL3
Keywords: ogc,staplus,sensorthingsapi,IoT
License-File: LICENSE
Requires-Dist: demjson3>=3.0.5
Requires-Dist: furl>=2.1.3
Requires-Dist: geojson>=2.5.0
Requires-Dist: jsonpickle>=2.0.0
Requires-Dist: requests>=2.26.0
Requires-Dist: jsonpatch
Requires-Dist: python-dateutil
Requires-Dist: pillow
Requires-Dist: sd-frost-sta-client
Dynamic: author
Dynamic: author-email
Dynamic: description
Dynamic: description-content-type
Dynamic: home-page
Dynamic: keywords
Dynamic: license
Dynamic: license-file
Dynamic: requires-dist
Dynamic: summary
